<?xml version="1.0" encoding="UTF-8"?>
<beans xmlns="http://www.springframework.org/schema/beans"
    xmlns:xsi="http://www.w3.org/2001/XMLSchema-instance" xmlns:context="http://www.springframework.org/schema/context"
    xmlns:mvc="http://www.springframework.org/schema/mvc"
    xsi:schemaLocation="http://www.springframework.org/schema/beans http://www.springframework.org/schema/beans/spring-beans-4.2.xsd
        http://www.springframework.org/schema/context http://www.springframework.org/schema/context/spring-context-4.2.xsd
        http://www.springframework.org/schema/mvc http://www.springframework.org/schema/mvc/spring-mvc-4.2.xsd">




    <context:annotation-config />
    <!-- 配置自动扫描的包，完成 Bean 的创建和自动依赖注入的功能 -->
    <context:component-scan base-package="com.madded.FirstSpringMVC.controller" />
    
    
    <!--使用默认的Servlet来响应静态文件 详见 1.2 -->
    <mvc:default-servlet-handler/>

    <!-- 开启注解驱动 详见 1.2 -->
    <mvc:annotation-driven/>
    

    <!-- 配置视图解析器 -->
    <bean class="org.springframework.web.servlet.view.InternalResourceViewResolver">
        <property name="prefix" value="/WEB-INF/views/"></property>
        <property name="suffix" value=".jsp"></property>
    </bean>

</beans> 